{
  "users": [
    {
      "id": "GCGrnNxyb54UJQxjMH21M",
      "email": "jeen0202@korea.ac.kr",
      "password": "111111",
      "displayName": "jeen0202"
    },
    {
      "id": "f3GK4Uzh2zujSiluzjoDD",
      "email": "jeen02",
      "password": "1111",
      "displayName": "jeen02"
    }
  ],
  "topics": [
    {
      "id": "9qLptknnPaDuUkK493jJ8",
      "title": "Express.js",
      "description": "Express.js is ....",
      "user_id": "GCGrnNxyb54UJQxjMH21M"
    },
    {
      "id": "0VI7cmTtcFCMuzSlbQPgV",
      "title": "OAuth 2.0",
      "description": "OAuth 2.0 is ...",
      "user_id": "f3GK4Uzh2zujSiluzjoDD"
    }
  ]
}